LICENSE
README.md
setup.py
steam_api/__init__.py
steam_api/auth.py
steam_api/core.py
steam_wrapper_api.egg-info/PKG-INFO
steam_wrapper_api.egg-info/SOURCES.txt
steam_wrapper_api.egg-info/dependency_links.txt
steam_wrapper_api.egg-info/requires.txt
steam_wrapper_api.egg-info/top_level.txt