Metadata-Version: 2.1
Name: steam-wrapper-api
Version: 0.1
Summary: unofficial steam API wrapper
Author: Gabriel Batistuta
Author-email: batistutag190@gmail.com
License: MIT License
Keywords: steam,wrapper,api
License-File: LICENSE
